LICENSE
MANIFEST.in
README.txt
buildout.cfg
setup.py
docs/HISTORY.txt
docs/README.txt
docs/sequence.png
docs/sequence.uml
src/ztfy/__init__.py
src/ztfy.scheduler.egg-info/PKG-INFO
src/ztfy.scheduler.egg-info/PKG-INFO.orig
src/ztfy.scheduler.egg-info/SOURCES.txt
src/ztfy.scheduler.egg-info/dependency_links.txt
src/ztfy.scheduler.egg-info/entry_points.txt
src/ztfy.scheduler.egg-info/namespace_packages.txt
src/ztfy.scheduler.egg-info/not-zip-safe
src/ztfy.scheduler.egg-info/requires.txt
src/ztfy.scheduler.egg-info/top_level.txt
src/ztfy/scheduler/__init__.py
src/ztfy/scheduler/configure.zcml
src/ztfy/scheduler/events.py
src/ztfy/scheduler/interfaces.py
src/ztfy/scheduler/jobstore.py
src/ztfy/scheduler/manager.py
src/ztfy/scheduler/meta.zcml
src/ztfy/scheduler/metaconfigure.py
src/ztfy/scheduler/process.py
src/ztfy/scheduler/security.py
src/ztfy/scheduler/security.zcml
src/ztfy/scheduler/ssh.py
src/ztfy/scheduler/task.py
src/ztfy/scheduler/url.py
src/ztfy/scheduler/vocabulary.py
src/ztfy/scheduler/zodb.py
src/ztfy/scheduler/browser/__init__.py
src/ztfy/scheduler/browser/configure.zcml
src/ztfy/scheduler/browser/interfaces.py
src/ztfy/scheduler/browser/manager.py
src/ztfy/scheduler/browser/ssh.py
src/ztfy/scheduler/browser/task.py
src/ztfy/scheduler/browser/url.py
src/ztfy/scheduler/browser/zodb.py
src/ztfy/scheduler/browser/templates/jobs.pt
src/ztfy/scheduler/doctests/README.txt
src/ztfy/scheduler/generations/__init__.py
src/ztfy/scheduler/generations/configure.zcml
src/ztfy/scheduler/generations/evolve1.py
src/ztfy/scheduler/generations/install.py
src/ztfy/scheduler/locales/ztfy.scheduler.pot
src/ztfy/scheduler/locales/en/LC_MESSAGES/ztfy.scheduler.mo
src/ztfy/scheduler/locales/en/LC_MESSAGES/ztfy.scheduler.po
src/ztfy/scheduler/locales/fr/LC_MESSAGES/ztfy.scheduler.mo
src/ztfy/scheduler/locales/fr/LC_MESSAGES/ztfy.scheduler.po
src/ztfy/scheduler/tests/__init__.py
src/ztfy/scheduler/tests/test_schedulerdocs.py
src/ztfy/scheduler/tests/test_schedulerdocstrings.py