Metadata-Version: 1.1
Name: ztfy.scheduler
Version: 0.5.0
Summary: ZTFY scheduler package for ZTK/ZopeApp
Home-page: http://www.ztfy.org
Author: Thierry Florac
Author-email: tflorac@ulthar.net
License: ZPL
Keywords: ZTFY scheduler for Zope3
Platform: UNKNOWN
Classifier: License :: OSI Approved :: Zope Public License
Classifier: Development Status :: 4 - Beta
Classifier: Programming Language :: Python
Classifier: Framework :: Zope3
Classifier: Topic :: Software Development :: Libraries :: Python Modules
